Workbook
Name BackOfficeWage: Table1[[#Totals],[Total cost per year(AZN)]]
Name capital_expenditure: Depreciation!$B$5
Name Cost_for_business_per_kWh: 'Wages & Rent'!$N$15
Name cost_per_kwh: Revenue!$G$2
Name depreciation: Depreciation!$B$6:$L$6
Name depreciation_amount: Depreciation!$I$2
Name depreciation_percentage: Depreciation!$I$2
Name depreciation_value: Depreciation!$I$2
Name ending_value: Depreciation!$L$7
Name Energy_consumption_kWh_sqm_warehouse: 'Wages & Rent'!$N$11
Name Energy_consumption_office_kWh_sqm: 'Wages & Rent'!$N$13
Name expenses_example: 'Income statement'!$C$13
Name expenses_range: 'Sensitivity cases'!$J$5:$J$15
Name growth_sale_volume: Revenue!$G$2
Name income_tax: 'Income statement'!$D$2
Name inflation_rate_Azerbaijan: 'Cash flow statement'!$B$14
Name inflation_rate_Eurozone: 'Cash flow statement'!$B$15
Name Net_income: 'Income statement'!$B$16:$L$16
Name NPV_Euro: 'Cash flow statement'!$B$21
Name NPV_Manat: 'Cash flow statement'!$B$20
Name perpetuity_growth_rate: 'Cash flow statement'!$B$18
Name Range: 'Sensitivity cases'!$G$5:$G$15
Name revenue: Revenue!$B$7:$L$7
Name selling_price_range: 'Sensitivity cases'!$H$5:$H$15
Name SiteOperationWage: Table2[[#Totals],[Total cost per year(AZN)]]
Name spot_exchange_rate: 'Cash flow statement'!$B$13
Name TotalRent: rent_utility_fee[[#Totals],[Average cost per year AZN]]
Name TotalUtility: rent_utility_fee[[#Totals],[Energy cost py]]
Name WACC: WACC!$B$9

Sheet Cash flow statement
A1: Engie company
A2: Cash Flow Statement
A3: [AZN Manat]
B4: {=_xlfn.SEQUENCE(1,11,0)} -> 0 | C4: 1 | D4: 2 | E4: 3 | F4: 4 | G4: 5 | H4: 6 | I4: 7 | J4: 8 | K4: 9 | L4: 10
A5: Net income | B5: {=Net_income} -> 0 | C5: 316334.72 | D5: 329576.32 | E5: 331382.72 | F5: 323774.72 | G5: 328285.92 | H5: 321177.12 | I5: 322885.12 | J5: 320431.52 | K5: 331956.32 | L5: 321289.92
A6: Depreciation | B6: {=depreciation} -> 0 | C6: 3229610.8 | D6: 3229610.8 | E6: 3229610.8 | F6: 3229610.8 | G6: 3229610.8 | H6: 3229610.8 | I6: 3229610.8 | J6: 3229610.8 | K6: 3229610.8 | L6: 3229610.8
A7: Operating cash flow | B7: =SUM(B5:B6) -> 0 | C7: =SUM(C5:C6) -> 3545945.5 | D7: =SUM(D5:D6) -> 3559187.1 | E7: =SUM(E5:E6) -> 3560993.5 | F7: =SUM(F5:F6) -> 3553385.5 | G7: =SUM(G5:G6) -> 3557896.7 | H7: =SUM(H5:H6) -> 3550787.9 | I7: =SUM(I5:I6) -> 3552495.9 | ... L7: =SUM(L5:L6) -> 3550900.7
A8: Initial Investment | B8: =-capital_expenditure -> -80740270 | L8: =ending_value -> 48444162
A9: Terminal value | L9: =(L7*(1+perpetuity_growth_rate))/(WACC-perpetuity_growth_rate) -> 1.0997385e+08
A10: Incremental CF | B10: =SUM(B7:B8) -> -80740270 | C10: =SUM(C7:C8) -> 3545945.5 | D10: =SUM(D7:D8) -> 3559187.1 | E10: =SUM(E7:E8) -> 3560993.5 | F10: =SUM(F7:F8) -> 3553385.5 | G10: =SUM(G7:G8) -> 3557896.7 | H10: =SUM(H7:H8) -> 3550787.9 | I10: =SUM(I7:I8) -> 3552495.9 | ... K10: =SUM(K7:K8) -> 3561567.1 | L10: =SUM(L7:L9) -> 1.6196891e+08
A12: Expected exchange rate based on PPP | B12: =B13 -> 1.6384 | C12: =B12*(1+(inflation_rate_Azerbaijan-inflation_rate_Eurozone)) -> 1.6908288 | D12: =C12*(1+(inflation_rate_Azerbaijan-inflation_rate_Eurozone)) -> 1.7449353 | E12: =D12*(1+(inflation_rate_Azerbaijan-inflation_rate_Eurozone)) -> 1.8007733 | F12: =E12*(1+(inflation_rate_Azerbaijan-inflation_rate_Eurozone)) -> 1.858398 | G12: =F12*(1+(inflation_rate_Azerbaijan-inflation_rate_Eurozone)) -> 1.9178667 | H12: =G12*(1+(inflation_rate_Azerbaijan-inflation_rate_Eurozone)) -> 1.9792385 | I12: =H12*(1+(inflation_rate_Azerbaijan-inflation_rate_Eurozone)) -> 2.0425741 | J12: =I12*(1+(inflation_rate_Azerbaijan-inflation_rate_Eurozone)) -> 2.1079365 | ... L12: =K12*(1+(inflation_rate_Azerbaijan-inflation_rate_Eurozone)) -> 2.2450029
A13: Spot exchange rate | B13: =1.6384 -> 1.6384 | C13: Manat/Euro
A14: Inflation rate in Azerbaijan | B14: 0.123
A15: Inflation rate in Eurozone | B15: 0.091
A16: Nominal return rate | B16: =WACC -> 0.060160384
A17: Real return rate | B17: =B16+(inflation_rate_Azerbaijan-inflation_rate_Eurozone) -> 0.092160384
A18: Perpetuity growth rate | B18: =2.7% -> 0.027
A20: NPV in Manat | B20: =NPV(B17,C10:L10)+B10 -> 7460203.5
A21: NPV in Euro | B21: =NPV_Manat/spot_exchange_rate -> 4553346.9
A22: IRR | B22: =IFERROR(IRR(B10:L10),"") -> 0.10340763
A23: Payback normal | F23: Payback discounted
B24: Year | C24: Project A | D24: Difference | G24: Year | H24: Project A | I24: PV (CF) | J24: Accumulated
B25: 0 | C25: {=TRANSPOSE(B10:L10)} -> -80740270 | G25: 0 | H25: {=TRANSPOSE(B10:L10)} -> -80740270 | I25: =-PV($B$17,G25,0,H25) -> -80740270 | J25: =I25 -> -80740270
B26: 1 | C26: 3545945.5 | D26: =C26+C25 -> -77194325 | G26: 1 | H26: 3545945.5 | I26: =-PV($B$17,G26,0,H26) -> 3246726 | J26: =J25+I26 -> -77493544
B27: 2 | C27: 3559187.1 | D27: =C27+D26 -> -73635137 | G27: 2 | H27: 3559187.1 | I27: =-PV($B$17,G27,0,H27) -> 2983856.8 | J27: =J26+I27 -> -74509687
B28: 3 | C28: 3560993.5 | D28: =C28+D27 -> -70074144 | G28: 3 | H28: 3560993.5 | I28: =-PV($B$17,G28,0,H28) -> 2733455 | J28: =J27+I28 -> -71776232
B29: 4 | C29: 3553385.5 | D29: =C29+D28 -> -66520758 | G29: 4 | H29: 3553385.5 | I29: =-PV($B$17,G29,0,H29) -> 2497449.1 | J29: =J28+I29 -> -69278783
B30: 5 | C30: 3557896.7 | D30: =C30+D29 -> -62962862 | G30: 5 | H30: 3557896.7 | I30: =-PV($B$17,G30,0,H30) -> 2289608.6 | J30: =J29+I30 -> -66989175
B31: 6 | C31: 3550787.9 | D31: =C31+D30 -> -59412074 | G31: 6 | H31: 3550787.9 | I31: =-PV($B$17,G31,0,H31) -> 2092214.6 | J31: =J30+I31 -> -64896960
B32: 7 | C32: 3552495.9 | D32: =C32+D31 -> -55859578 | G32: 7 | H32: 3552495.9 | I32: =-PV($B$17,G32,0,H32) -> 1916587.5 | J32: =J31+I32 -> -62980373
B33: 8 | C33: 3550042.3 | D33: =C33+D32 -> -52309536 | G33: 8 | H33: 3550042.3 | I33: =-PV($B$17,G33,0,H33) -> 1753647 | J33: =J32+I33 -> -61226726
B34: 9 | C34: 3561567.1 | D34: =C34+D33 -> -48747968 | G34: 9 | H34: 3561567.1 | I34: =-PV($B$17,G34,0,H34) -> 1610880.6 | J34: =J33+I34 -> -59615845
B35: 10 | C35: 1.6196891e+08 | D35: =C35+D34 -> 1.1322094e+08 | G35: 10 | H35: 1.6196891e+08 | I35: =-PV($B$17,G35,0,H35) -> 67076048 | J35: =J34+I35 -> 7460203.5
A39: Source for other rates
A40: Require rate of return
A41: Inflation rate in Azerbaijan
A42: Inflation rate in Eurozone
A43: Spot exchange rate

Sheet Income statement
A1: Engie company
A2: Income Statement | C2: Tax | D2: 0.2
A3: [AZN manat]
B4: {=_xlfn.SEQUENCE(1,11,0)} -> 0 | C4: 1 | D4: 2 | E4: 3 | F4: 4 | G4: 5 | H4: 6 | I4: 7 | J4: 8 | K4: 9 | L4: 10
A5: Reveneue | B5: {=revenue} -> 0 | C5: 6000000 | D5: 6000000 | E5: 6000000 | F5: 6000000 | G5: 6000000 | H5: 6000000 | I5: 6000000 | J5: 6000000 | K5: 6000000 | L5: 6000000
A6: Expenses
A7: Maintenance | B7: 0 | C7: =RANDBETWEEN(51000,81000) -> 71164 | D7: =RANDBETWEEN(51000,81000) -> 54612 | E7: =RANDBETWEEN(51000,81000) -> 52354 | F7: =RANDBETWEEN(51000,81000) -> 61864 | G7: =RANDBETWEEN(51000,81000) -> 56225 | H7: =RANDBETWEEN(51000,81000) -> 65111 | I7: =RANDBETWEEN(51000,81000) -> 62976 | J7: =RANDBETWEEN(51000,81000) -> 66043 | ... L7: =RANDBETWEEN(51000,81000) -> 64970 | M7: Source
A8: Administration | B8: 0 | C8: {=(BackOfficeWage+SiteOperationWage)} -> 2050443 | D8: {=(BackOfficeWage+SiteOperationWage)} -> 2050443 | E8: {=(BackOfficeWage+SiteOperationWage)} -> 2050443 | F8: {=(BackOfficeWage+SiteOperationWage)} -> 2050443 | G8: {=(BackOfficeWage+SiteOperationWage)} -> 2050443 | H8: {=(BackOfficeWage+SiteOperationWage)} -> 2050443 | I8: {=(BackOfficeWage+SiteOperationWage)} -> 2050443 | J8: {=(BackOfficeWage+SiteOperationWage)} -> 2050443 | ... L8: {=(BackOfficeWage+SiteOperationWage)} -> 2050443
A9: Rent and Overhead | B9: 0 | C9: {=TotalRent} -> 159600 | D9: {=TotalRent} -> 159600 | E9: {=TotalRent} -> 159600 | F9: {=TotalRent} -> 159600 | G9: {=TotalRent} -> 159600 | H9: {=TotalRent} -> 159600 | I9: {=TotalRent} -> 159600 | J9: {=TotalRent} -> 159600 | ... L9: {=TotalRent} -> 159600
A10: Utility | B10: 0 | C10: {=TotalUtility} -> 18763.8 | D10: {=TotalUtility} -> 18763.8 | E10: {=TotalUtility} -> 18763.8 | F10: {=TotalUtility} -> 18763.8 | G10: {=TotalUtility} -> 18763.8 | H10: {=TotalUtility} -> 18763.8 | I10: {=TotalUtility} -> 18763.8 | J10: {=TotalUtility} -> 18763.8 | ... L10: {=TotalUtility} -> 18763.8
A11: Insurance | B11: 0 | C11: =15000*'Capital requirement'!$B$14 -> 75000 | D11: =15000*'Capital requirement'!$B$14 -> 75000 | E11: =15000*'Capital requirement'!$B$14 -> 75000 | F11: =15000*'Capital requirement'!$B$14 -> 75000 | G11: =15000*'Capital requirement'!$B$14 -> 75000 | H11: =15000*'Capital requirement'!$B$14 -> 75000 | I11: =15000*'Capital requirement'!$B$14 -> 75000 | J11: =15000*'Capital requirement'!$B$14 -> 75000 | ... L11: =15000*'Capital requirement'!$B$14 -> 75000
A12: Depreciation & Amortization | B12: {=depreciation} -> 0 | C12: 3229610.8 | D12: 3229610.8 | E12: 3229610.8 | F12: 3229610.8 | G12: 3229610.8 | H12: 3229610.8 | I12: 3229610.8 | J12: 3229610.8 | K12: 3229610.8 | L12: 3229610.8
A13: Total Expenses | B13: =SUM(B7:B12) -> 0 | C13: =SUM(C7:C12) -> 5604581.6 | D13: =SUM(D7:D12) -> 5588029.6 | E13: =SUM(E7:E12) -> 5585771.6 | F13: =SUM(F7:F12) -> 5595281.6 | G13: =SUM(G7:G12) -> 5589642.6 | H13: =SUM(H7:H12) -> 5598528.6 | I13: =SUM(I7:I12) -> 5596393.6 | ... L13: =SUM(L7:L12) -> 5598387.6
A14: Earnings Before Tax | B14: =B5-B13 -> 0 | C14: =C5-C13 -> 395418.4 | D14: =D5-D13 -> 411970.4 | E14: =E5-E13 -> 414228.4 | F14: =F5-F13 -> 404718.4 | G14: =G5-G13 -> 410357.4 | H14: =H5-H13 -> 401471.4 | I14: =I5-I13 -> 403606.4 | ... L14: =L5-L13 -> 401612.4
A15: Taxes | B15: =B14*income_tax -> 0 | C15: =C14*income_tax -> 79083.679 | D15: =D14*income_tax -> 82394.079 | E15: =E14*income_tax -> 82845.679 | F15: =F14*income_tax -> 80943.679 | G15: =G14*income_tax -> 82071.479 | H15: =H14*income_tax -> 80294.279 | I15: =I14*income_tax -> 80721.279 | ... L15: =L14*income_tax -> 80322.479
A16: Net income | B16: =B14-B15 -> 0 | C16: =C14-C15 -> 316334.72 | D16: =D14-D15 -> 329576.32 | E16: =E14-E15 -> 331382.72 | F16: =F14-F15 -> 323774.72 | G16: =G14-G15 -> 328285.92 | H16: =H14-H15 -> 321177.12 | I16: =I14-I15 -> 322885.12 | ... L16: =L14-L15 -> 321289.92

Sheet Capital requirement
A1: Engie company
A2: Capital requirement
A3: [AZN Manat]
B4: 0
A5: Turbine capital expenditure
A6: Wind turbine | B6: =B19*B15*B14 -> 19.5
A7: Balance of system
A8: Support structure | B8: =B20*B15*B14+3*80*B21*3*B14+B23*B14 -> 15.43345
A9: Electrical Infrastructure | B9: =B24*800*B14+B26*25000+SUM(B28:B29)*B15*B14 -> 11.8465
A10: Installation | B10: =B30*B14 -> 2.5
A11: Total investment | B11: =SUM(B6:B10) -> 49.27995 | C11: mil
B12: =B11*spot_exchange_rate -> 80.74027 | C12: mil
A14: Number of turbines | B14: 5
A15: Single turbine capacity | B15: 3 | C15: MW
A17: Assumptions based on the information from the source
A18: Capex items | B18: Estimated price in m€ | C18: Unit | D18: Other assumpions
A19: Turbine | B19: 1.3 | C19: per MW
A20: Platform | B20: 0.894 | C20: per MW | D20: Hexafloat turbine
A21: Moorings | B21: 0.0005 | C21: per meter | D21: Moorings cost = 3*sea depth*3mooring lines for each turbine
D22: Estimated sea depth - 80 meters
A23: Anchors | B23: 0.04469 | C23: per turbine | D23: Estimated price for 3 anchors
A24: Array marine cables | B24: 0.0003 | C24: per meter | D24: Turbines are connected to the offshore substantion by array marine cables
D25: Estimated distance between turbines and offshore electrical substantion - 800 meters
A26: Export marine cables | B26: 0.0004 | C26: per meter | D26: Export marine cables connect offshore electrical substantion with onshore electrical substantion
D27: Estimated distance betweet two electrical substantions - 25km
A28: Offshore electrical substantion | B28: 0.0311 | C28: per MW
A29: Onshore electrical substantion | B29: 0.012 | C29: per MW
A30: Installation | B30: 0.5 | C30: per turbine

Sheet Depreciation
A1: Engie company
A2: Depreciation | C2: Life time | D2: 10 | F2: Straight-line method | I2: =capital_expenditure/25 -> 3229610.8
A3: [AZN Manat]
B4: {=_xlfn.SEQUENCE(1,11,0)} -> 0 | C4: 1 | D4: 2 | E4: 3 | F4: 4 | G4: 5 | H4: 6 | I4: 7 | J4: 8 | K4: 9 | L4: 10
A5: Initial value | B5: ='Capital requirement'!B12*10^6 -> 80740270 | C5: =B7 -> 80740270 | D5: =C7 -> 77510659 | E5: =D7 -> 74281048 | F5: =E7 -> 71051438 | G5: =F7 -> 67821827 | H5: =G7 -> 64592216 | I5: =H7 -> 61362605 | J5: =I7 -> 58132994 | ... L5: =K7 -> 51673773
A6: Depreciation | B6: 0 | C6: =depreciation_percentage -> 3229610.8 | D6: =depreciation_percentage -> 3229610.8 | E6: =depreciation_percentage -> 3229610.8 | F6: =depreciation_percentage -> 3229610.8 | G6: =depreciation_percentage -> 3229610.8 | H6: =depreciation_percentage -> 3229610.8 | I6: =depreciation_percentage -> 3229610.8 | J6: =depreciation_percentage -> 3229610.8 | ... L6: =depreciation_percentage -> 3229610.8
A7: Residual value | B7: =B5-B6 -> 80740270 | C7: =C5-C6 -> 77510659 | D7: =D5-D6 -> 74281048 | E7: =E5-E6 -> 71051438 | F7: =F5-F6 -> 67821827 | G7: =G5-G6 -> 64592216 | H7: =H5-H6 -> 61362605 | I7: =I5-I6 -> 58132994 | ... L7: =L5-L6 -> 48444162

Sheet Revenue
A1: Engie company
A2: Revenue | E2: Cost per kwh | G2: 0.06
A3: [AZN Manat]
B4: {=_xlfn.SEQUENCE(1,11,0)} -> 0 | C4: 1 | D4: 2 | E4: 3 | F4: 4 | G4: 5 | H4: 6 | I4: 7 | J4: 8 | K4: 9 | L4: 10
A5: Number of turbine | C5: 5 | D5: 5 | E5: 5 | F5: 5 | G5: 5 | H5: 5 | I5: 5 | J5: 5 | K5: 5 | L5: 5
A6: Volume (kwh) | C6: =20000000 -> 20000000 | D6: =20000000 -> 20000000 | E6: =20000000 -> 20000000 | F6: =20000000 -> 20000000 | G6: =20000000 -> 20000000 | H6: =20000000 -> 20000000 | I6: =20000000 -> 20000000 | J6: =20000000 -> 20000000 | ... L6: =20000000 -> 20000000
A7: Revenues | C7: =PRODUCT(C5:C6)*cost_per_kwh -> 6000000 | D7: =PRODUCT(D5:D6)*cost_per_kwh -> 6000000 | E7: =PRODUCT(E5:E6)*cost_per_kwh -> 6000000 | F7: =PRODUCT(F5:F6)*cost_per_kwh -> 6000000 | G7: =PRODUCT(G5:G6)*cost_per_kwh -> 6000000 | H7: =PRODUCT(H5:H6)*cost_per_kwh -> 6000000 | I7: =PRODUCT(I5:I6)*cost_per_kwh -> 6000000 | J7: =PRODUCT(J5:J6)*cost_per_kwh -> 6000000 | ... L7: =PRODUCT(L5:L6)*cost_per_kwh -> 6000000

Sheet Wages & Rent
A1: Engie company
A2: Wages & Rent
A3: [AZN Manat]
A4: Back office and asset management | B4: Average salary in Azerbaijan py(AZN) | C4: Number of employees | D4: Total cost per year(AZN) | E4: Sources | G4: Site Operations | H4: Average salary in Azerbaijan py(AZN) | I4: Number of employees | J4: Total cost per year(AZN) | K4: Sources | M4: Logistics/operational base | N4: Size m2 | O4: Avgerage Cost per month AZN | P4: Average cost per year AZN | Q4: Energy consumption py(KWh) | R4: Energy cost py | S4: Sources
A5: General manager | B5: 56880 | C5: 1 | D5: =Table1[[#This Row],[Average salary in Azerbaijan py(AZN)]]*Table1[[#This Row],[Number of employees]] -> 56880 | E5: Source | G5: Site Manager | H5: 62460 | I5: 1 | J5: =Table2[[#This Row],[Average salary in Azerbaijan py(AZN)]]*Table2[[#This Row],[Number of employees]] -> 62460 | K5: Source | M5: Indoor facility/office | N5: 300 | O5: 2000 | P5: =O5*12 -> 24000 | Q5: =N5*Energy_consumption_office_kWh_sqm -> 49800 | R5: =Q5*Cost_for_business_per_kWh -> 5478 | S5: Source
A6: Finance Manager | B6: 73020 | C6: 1 | D6: =Table1[[#This Row],[Average salary in Azerbaijan py(AZN)]]*Table1[[#This Row],[Number of employees]] -> 73020 | E6: Source | G6: Control Room operator | H6: 10080 | I6: 5 | J6: =Table2[[#This Row],[Average salary in Azerbaijan py(AZN)]]*Table2[[#This Row],[Number of employees]] -> 50400 | K6: Source | M6: Indoor warehouse facilities | N6: 500 | O6: 1700 | P6: =O6*12 -> 20400 | Q6: =N6*Energy_consumption_kWh_sqm_warehouse -> 33550 | R6: =Q6*Cost_for_business_per_kWh -> 3690.5 | S6: Source
A7: Accountant | B7: 24860 | C7: 3 | D7: =Table1[[#This Row],[Average salary in Azerbaijan py(AZN)]]*Table1[[#This Row],[Number of employees]] -> 74580 | E7: Source | G7: Shift Supervisor | H7: 36000 | I7: 3 | J7: =Table2[[#This Row],[Average salary in Azerbaijan py(AZN)]]*Table2[[#This Row],[Number of employees]] -> 108000 | K7: Source | M7: Outdoor storage space | N7: 800 | O7: 5100 | P7: =O7*12 -> 61200 | Q7: =N7*Energy_consumption_kWh_sqm_warehouse -> 53680 | R7: =Q7*Cost_for_business_per_kWh -> 5904.8 | S7: Source
A8: Legal | B8: 46840 | C8: 1 | D8: =Table1[[#This Row],[Average salary in Azerbaijan py(AZN)]]*Table1[[#This Row],[Number of employees]] -> 46840 | E8: Source | G8: Admin Support | H8: 12000 | I8: 4 | J8: =Table2[[#This Row],[Average salary in Azerbaijan py(AZN)]]*Table2[[#This Row],[Number of employees]] -> 48000 | K8: Source | M8: Parking space | N8: 500 | O8: 4500 | P8: =O8*12 -> 54000 | Q8: =N8*Energy_consumption_kWh_sqm_warehouse -> 33550 | R8: =Q8*Cost_for_business_per_kWh -> 3690.5 | S8: Source
A9: Procurement Manager | B9: 23980 | C9: 2 | D9: =Table1[[#This Row],[Average salary in Azerbaijan py(AZN)]]*Table1[[#This Row],[Number of employees]] -> 47960 | E9: Source | G9: Plant Technicians | H9: 12600 | I9: 8 | J9: =Table2[[#This Row],[Average salary in Azerbaijan py(AZN)]]*Table2[[#This Row],[Number of employees]] -> 100800 | K9: Source | M9: Total | P9: =SUBTOTAL(109,rent_utility_fee[Average cost per year AZN]) -> 159600 | R9: =SUBTOTAL(109,rent_utility_fee[Energy cost py]) -> 18763.8
A10: Contract Manager | B10: 41820 | C10: 1 | D10: =Table1[[#This Row],[Average salary in Azerbaijan py(AZN)]]*Table1[[#This Row],[Number of employees]] -> 41820 | E10: Source | G10: WTG Technicians | H10: 32700 | I10: 5 | J10: =Table2[[#This Row],[Average salary in Azerbaijan py(AZN)]]*Table2[[#This Row],[Number of employees]] -> 163500 | K10: Source
A11: Insurance manager | B11: 33400 | C11: 1 | D11: =Table1[[#This Row],[Average salary in Azerbaijan py(AZN)]]*Table1[[#This Row],[Number of employees]] -> 33400 | E11: Source | G11: Store room operator | H11: 15800 | I11: 4 | J11: =Table2[[#This Row],[Average salary in Azerbaijan py(AZN)]]*Table2[[#This Row],[Number of employees]] -> 63200 | K11: Source | M11: Energy consumption kWh/sqm warehouse | N11: =67.1 -> 67.1
A12: Project administration | B12: 31660 | C12: 3 | D12: =Table1[[#This Row],[Average salary in Azerbaijan py(AZN)]]*Table1[[#This Row],[Number of employees]] -> 94980 | E12: Source | G12: Offshore engineer manager | H12: 42960 | I12: 3 | J12: =Table2[[#This Row],[Average salary in Azerbaijan py(AZN)]]*Table2[[#This Row],[Number of employees]] -> 128880 | K12: Source | O12: Source
A13: Performance Engineer | B13: 36500 | C13: 2 | D13: =Table1[[#This Row],[Average salary in Azerbaijan py(AZN)]]*Table1[[#This Row],[Number of employees]] -> 73000 | E13: Source | G13: Subsea enginner | H13: 39000 | I13: 5 | J13: =Table2[[#This Row],[Average salary in Azerbaijan py(AZN)]]*Table2[[#This Row],[Number of employees]] -> 195000 | K13: Source | M13: Energy consumption office kWh/sqm | N13: 166 | O13: Source
A14: Total | B14: =SUBTOTAL(109,Table1[Average salary in Azerbaijan py(AZN)]) -> 368960 | C14: =SUM(Table1[Number of employees]) -> 15 | D14: =SUM(Table1[Total cost per year(AZN)]) -> 542480 | G14: Turbine platform engineer | H14: 14760 | I14: 7 | J14: =Table2[[#This Row],[Average salary in Azerbaijan py(AZN)]]*Table2[[#This Row],[Number of employees]] -> 103320 | K14: Source
G15: Electrical Engineer | H15: 36700 | I15: 8 | J15: =Table2[[#This Row],[Average salary in Azerbaijan py(AZN)]]*Table2[[#This Row],[Number of employees]] -> 293600 | K15: Source | M15: Cost for business per kWh | N15: 0.11 | O15: Source
G16: Control system manager | H16: 31000 | I16: 2 | J16: =Table2[[#This Row],[Average salary in Azerbaijan py(AZN)]]*Table2[[#This Row],[Number of employees]] -> 62000 | K16: Source
G17: System engineer | H17: 31001 | I17: 3 | J17: =Table2[[#This Row],[Average salary in Azerbaijan py(AZN)]]*Table2[[#This Row],[Number of employees]] -> 93003 | K17: Source
G18: HV Switching technicians | H18: 17900 | I18: 2 | J18: =Table2[[#This Row],[Average salary in Azerbaijan py(AZN)]]*Table2[[#This Row],[Number of employees]] -> 35800 | K18: Source
G19: Total | H19: =SUBTOTAL(109,Table2[Average salary in Azerbaijan py(AZN)]) -> 394961 | I19: =SUM(Table2[Number of employees]) -> 60 | J19: =SUM(Table2[Total cost per year(AZN)]) -> 1507963

Sheet WACC
A1: Engie company
A2: WACC
A3: [Euro]
A4: Market cap (mil) | B4: 29198 | C4: Engie finance yahoo | E4: Risk-free rate | F4: 0.027 | G4: 10-year government bond in France
A5: Total debt (mil) | B5: 41048 | C5: Engie finance yahoo | E5: Beta | F5: 1.13 | G5: beta
A6: V | B6: =B4+B5 -> 70246 | E6: Market risk premium | F6: 0.0675 | G6: market risk premium
A7: E/V | B7: =B4/B6 -> 0.41565356 | E7: Cost of equity | F7: =F4+F5*F6 -> 0.103275
A8: D/V | B8: =1-B7 -> 0.58434644
A9: WACC | B9: =B7*F7+B8*F11*(1-F15) -> 0.060160384 | E9: Interest expense | F9: 1601000 | G9: Engie finance yahoo
E10: Average debt | F10: =(41048000+37937000)/2 -> 39492500
E11: Cost of debt | F11: =F9/F10 -> 0.040539343
E13: Year | F13: 2021 | G13: 2020
E14: Tax rate | F14: 0.265 | G14: 0.28 | H14: Corporate tax rate
E15: Average tax rate | F15: =AVERAGE(F14:G14) -> 0.2725

Sheet Sensitivity cases
A1: Engie company
A2: Sensitivity cases with selling price and expenses
A3: [AZN Manat]
A4: Sensitivity cases | B4: Selling price | C4: Range | D4: Expenses | E4: Range | G4: Range | H4: Selling price | I4: Frequency price | J4: Expenses | K4: Frequency expenses | L4: Exchange rate | M4: NPV in Euro | O4: Cost per Mwh | P4: =cost_per_kwh*1000000 -> 60000
A5: 1 | B5: =RANDBETWEEN($P$4*(1+$G$5),$P$4*(1+$G$15)) -> 57914 | C5: =_xlfn.XLOOKUP(B5,selling_price_range,Range,"",-1) -> -0.04 | D5: =RANDBETWEEN($P$5*(1+$G$5),$P$5*(1+$G$15)) -> 5668512 | E5: =_xlfn.XLOOKUP(D5,expenses_range,Range,"",-1) -> 0.01 | G5: -0.05 | H5: =$P$4*(1+$G5) -> 57000 | I5: {=FREQUENCY(C5:C1004,G5:G15)} -> 111 | J5: =$P$5*(1+$G5) -> 5324352.5 | K5: {=FREQUENCY(E5:E1004,G5:G15)} -> 107 | L5: =spot_exchange_rate*(1+G5) -> 1.55648 | M5: =NPV_Manat/L5 -> 4792996.7 | O5: Expenses | P5: =expenses_example -> 5604581.6
A6: 2 | B6: =RANDBETWEEN($P$4*(1+$G$5),$P$4*(1+$G$15)) -> 57678 | C6: =_xlfn.XLOOKUP(B6,selling_price_range,Range,"",-1) -> -0.04 | D6: =RANDBETWEEN($P$5*(1+$G$5),$P$5*(1+$G$15)) -> 5755635 | E6: =_xlfn.XLOOKUP(D6,expenses_range,Range,"",-1) -> 0.02 | G6: -0.04 | H6: =$P$4*(1+$G6) -> 57600 | I6: 96 | J6: =$P$5*(1+$G6) -> 5380398.3 | K6: 101 | L6: =spot_exchange_rate*(1+G6) -> 1.572864 | M6: =NPV_Manat/L6 -> 4743069.7
A7: 3 | B7: =RANDBETWEEN($P$4*(1+$G$5),$P$4*(1+$G$15)) -> 61022 | C7: =_xlfn.XLOOKUP(B7,selling_price_range,Range,"",-1) -> 0.01 | D7: =RANDBETWEEN($P$5*(1+$G$5),$P$5*(1+$G$15)) -> 5491990 | E7: =_xlfn.XLOOKUP(D7,expenses_range,Range,"",-1) -> -0.03 | G7: -0.03 | H7: =$P$4*(1+$G7) -> 58200 | I7: 94 | J7: =$P$5*(1+$G7) -> 5436444.2 | K7: 110 | L7: =spot_exchange_rate*(1+G7) -> 1.589248 | M7: =NPV_Manat/L7 -> 4694172
A8: 4 | B8: =RANDBETWEEN($P$4*(1+$G$5),$P$4*(1+$G$15)) -> 57826 | C8: =_xlfn.XLOOKUP(B8,selling_price_range,Range,"",-1) -> -0.04 | D8: =RANDBETWEEN($P$5*(1+$G$5),$P$5*(1+$G$15)) -> 5744916 | E8: =_xlfn.XLOOKUP(D8,expenses_range,Range,"",-1) -> 0.02 | G8: -0.02 | H8: =$P$4*(1+$G8) -> 58800 | I8: 111 | J8: =$P$5*(1+$G8) -> 5492490 | K8: 87 | L8: =spot_exchange_rate*(1+G8) -> 1.605632 | M8: =NPV_Manat/L8 -> 4646272.3
A9: 5 | B9: =RANDBETWEEN($P$4*(1+$G$5),$P$4*(1+$G$15)) -> 58404 | C9: =_xlfn.XLOOKUP(B9,selling_price_range,Range,"",-1) -> -0.03 | D9: =RANDBETWEEN($P$5*(1+$G$5),$P$5*(1+$G$15)) -> 5455766 | E9: =_xlfn.XLOOKUP(D9,expenses_range,Range,"",-1) -> -0.03 | G9: -0.01 | H9: =$P$4*(1+$G9) -> 59400 | I9: 97 | J9: =$P$5*(1+$G9) -> 5548535.8 | K9: 105 | L9: =spot_exchange_rate*(1+G9) -> 1.622016 | M9: =NPV_Manat/L9 -> 4599340.3
A10: 6 | B10: =RANDBETWEEN($P$4*(1+$G$5),$P$4*(1+$G$15)) -> 61616 | C10: =_xlfn.XLOOKUP(B10,selling_price_range,Range,"",-1) -> 0.02 | D10: =RANDBETWEEN($P$5*(1+$G$5),$P$5*(1+$G$15)) -> 5514614 | E10: =_xlfn.XLOOKUP(D10,expenses_range,Range,"",-1) -> -0.02 | G10: 0 | H10: =$P$4*(1+$G10) -> 60000 | I10: 96 | J10: =$P$5*(1+$G10) -> 5604581.6 | K10: 91 | L10: =spot_exchange_rate -> 1.6384 | M10: =NPV_Manat/L10 -> 4553346.9
A11: 7 | B11: =RANDBETWEEN($P$4*(1+$G$5),$P$4*(1+$G$15)) -> 60937 | C11: =_xlfn.XLOOKUP(B11,selling_price_range,Range,"",-1) -> 0.01 | D11: =RANDBETWEEN($P$5*(1+$G$5),$P$5*(1+$G$15)) -> 5445327 | E11: =_xlfn.XLOOKUP(D11,expenses_range,Range,"",-1) -> -0.03 | G11: 0.01 | H11: =$P$4*(1+$G11) -> 60600 | I11: 106 | J11: =$P$5*(1+$G11) -> 5660627.4 | K11: 105 | L11: =spot_exchange_rate*(1+G11) -> 1.654784 | M11: =NPV_Manat/L11 -> 4508264.2
A12: 8 | B12: =RANDBETWEEN($P$4*(1+$G$5),$P$4*(1+$G$15)) -> 61149 | C12: =_xlfn.XLOOKUP(B12,selling_price_range,Range,"",-1) -> 0.01 | D12: =RANDBETWEEN($P$5*(1+$G$5),$P$5*(1+$G$15)) -> 5516682 | E12: =_xlfn.XLOOKUP(D12,expenses_range,Range,"",-1) -> -0.02 | G12: 0.02 | H12: =$P$4*(1+$G12) -> 61200 | I12: 89 | J12: =$P$5*(1+$G12) -> 5716673.2 | K12: 100 | L12: =spot_exchange_rate*(1+G12) -> 1.671168 | M12: =NPV_Manat/L12 -> 4464065.6
A13: 9 | B13: =RANDBETWEEN($P$4*(1+$G$5),$P$4*(1+$G$15)) -> 59045 | C13: =_xlfn.XLOOKUP(B13,selling_price_range,Range,"",-1) -> -0.02 | D13: =RANDBETWEEN($P$5*(1+$G$5),$P$5*(1+$G$15)) -> 5501334 | E13: =_xlfn.XLOOKUP(D13,expenses_range,Range,"",-1) -> -0.02 | G13: 0.03 | H13: =$P$4*(1+$G13) -> 61800 | I13: 111 | J13: =$P$5*(1+$G13) -> 5772719.1 | K13: 89 | L13: =spot_exchange_rate*(1+G13) -> 1.687552 | M13: =NPV_Manat/L13 -> 4420725.1
A14: 10 | B14: =RANDBETWEEN($P$4*(1+$G$5),$P$4*(1+$G$15)) -> 58480 | C14: =_xlfn.XLOOKUP(B14,selling_price_range,Range,"",-1) -> -0.03 | D14: =RANDBETWEEN($P$5*(1+$G$5),$P$5*(1+$G$15)) -> 5872705 | E14: =_xlfn.XLOOKUP(D14,expenses_range,Range,"",-1) -> 0.04 | G14: 0.04 | H14: =$P$4*(1+$G14) -> 62400 | I14: 89 | J14: =$P$5*(1+$G14) -> 5828764.9 | K14: 105 | L14: =spot_exchange_rate*(1+G14) -> 1.703936 | M14: =NPV_Manat/L14 -> 4378218.2
A15: 11 | B15: =RANDBETWEEN($P$4*(1+$G$5),$P$4*(1+$G$15)) -> 61939 | C15: =_xlfn.XLOOKUP(B15,selling_price_range,Range,"",-1) -> 0.03 | D15: =RANDBETWEEN($P$5*(1+$G$5),$P$5*(1+$G$15)) -> 5852839 | E15: =_xlfn.XLOOKUP(D15,expenses_range,Range,"",-1) -> 0.04 | G15: 0.05 | H15: =$P$4*(1+$G15) -> 63000 | I15: 0 | J15: =$P$5*(1+$G15) -> 5884810.7 | K15: 0 | L15: =spot_exchange_rate*(1+G15) -> 1.72032 | M15: =NPV_Manat/L15 -> 4336520.8
A16: 12 | B16: =RANDBETWEEN($P$4*(1+$G$5),$P$4*(1+$G$15)) -> 61846 | C16: =_xlfn.XLOOKUP(B16,selling_price_range,Range,"",-1) -> 0.03 | D16: =RANDBETWEEN($P$5*(1+$G$5),$P$5*(1+$G$15)) -> 5717016 | E16: =_xlfn.XLOOKUP(D16,expenses_range,Range,"",-1) -> 0.02
A17: 13 | B17: =RANDBETWEEN($P$4*(1+$G$5),$P$4*(1+$G$15)) -> 61829 | C17: =_xlfn.XLOOKUP(B17,selling_price_range,Range,"",-1) -> 0.03 | D17: =RANDBETWEEN($P$5*(1+$G$5),$P$5*(1+$G$15)) -> 5568690 | E17: =_xlfn.XLOOKUP(D17,expenses_range,Range,"",-1) -> -0.01
A18: 14 | B18: =RANDBETWEEN($P$4*(1+$G$5),$P$4*(1+$G$15)) -> 62495 | C18: =_xlfn.XLOOKUP(B18,selling_price_range,Range,"",-1) -> 0.04 | D18: =RANDBETWEEN($P$5*(1+$G$5),$P$5*(1+$G$15)) -> 5453207 | E18: =_xlfn.XLOOKUP(D18,expenses_range,Range,"",-1) -> -0.03
A19: 15 | B19: =RANDBETWEEN($P$4*(1+$G$5),$P$4*(1+$G$15)) -> 61109 | C19: =_xlfn.XLOOKUP(B19,selling_price_range,Range,"",-1) -> 0.01 | D19: =RANDBETWEEN($P$5*(1+$G$5),$P$5*(1+$G$15)) -> 5532260 | E19: =_xlfn.XLOOKUP(D19,expenses_range,Range,"",-1) -> -0.02
A20: 16 | B20: =RANDBETWEEN($P$4*(1+$G$5),$P$4*(1+$G$15)) -> 60862 | C20: =_xlfn.XLOOKUP(B20,selling_price_range,Range,"",-1) -> 0.01 | D20: =RANDBETWEEN($P$5*(1+$G$5),$P$5*(1+$G$15)) -> 5534143 | E20: =_xlfn.XLOOKUP(D20,expenses_range,Range,"",-1) -> -0.02
A21: 17 | B21: =RANDBETWEEN($P$4*(1+$G$5),$P$4*(1+$G$15)) -> 62855 | C21: =_xlfn.XLOOKUP(B21,selling_price_range,Range,"",-1) -> 0.04 | D21: =RANDBETWEEN($P$5*(1+$G$5),$P$5*(1+$G$15)) -> 5673970 | E21: =_xlfn.XLOOKUP(D21,expenses_range,Range,"",-1) -> 0.01
A22: 18 | B22: =RANDBETWEEN($P$4*(1+$G$5),$P$4*(1+$G$15)) -> 59751 | C22: =_xlfn.XLOOKUP(B22,selling_price_range,Range,"",-1) -> -0.01 | D22: =RANDBETWEEN($P$5*(1+$G$5),$P$5*(1+$G$15)) -> 5523087 | E22: =_xlfn.XLOOKUP(D22,expenses_range,Range,"",-1) -> -0.02
A23: 19 | B23: =RANDBETWEEN($P$4*(1+$G$5),$P$4*(1+$G$15)) -> 58010 | C23: =_xlfn.XLOOKUP(B23,selling_price_range,Range,"",-1) -> -0.04 | D23: =RANDBETWEEN($P$5*(1+$G$5),$P$5*(1+$G$15)) -> 5568588 | E23: =_xlfn.XLOOKUP(D23,expenses_range,Range,"",-1) -> -0.01
A24: 20 | B24: =RANDBETWEEN($P$4*(1+$G$5),$P$4*(1+$G$15)) -> 61716 | C24: =_xlfn.XLOOKUP(B24,selling_price_range,Range,"",-1) -> 0.02 | D24: =RANDBETWEEN($P$5*(1+$G$5),$P$5*(1+$G$15)) -> 5682786 | E24: =_xlfn.XLOOKUP(D24,expenses_range,Range,"",-1) -> 0.01
A25: 21 | B25: =RANDBETWEEN($P$4*(1+$G$5),$P$4*(1+$G$15)) -> 57201 | C25: =_xlfn.XLOOKUP(B25,selling_price_range,Range,"",-1) -> -0.05 | D25: =RANDBETWEEN($P$5*(1+$G$5),$P$5*(1+$G$15)) -> 5384545 | E25: =_xlfn.XLOOKUP(D25,expenses_range,Range,"",-1) -> -0.04
A26: 22 | B26: =RANDBETWEEN($P$4*(1+$G$5),$P$4*(1+$G$15)) -> 62326 | C26: =_xlfn.XLOOKUP(B26,selling_price_range,Range,"",-1) -> 0.03 | D26: =RANDBETWEEN($P$5*(1+$G$5),$P$5*(1+$G$15)) -> 5533409 | E26: =_xlfn.XLOOKUP(D26,expenses_range,Range,"",-1) -> -0.02
A27: 23 | B27: =RANDBETWEEN($P$4*(1+$G$5),$P$4*(1+$G$15)) -> 61918 | C27: =_xlfn.XLOOKUP(B27,selling_price_range,Range,"",-1) -> 0.03 | D27: =RANDBETWEEN($P$5*(1+$G$5),$P$5*(1+$G$15)) -> 5349671 | E27: =_xlfn.XLOOKUP(D27,expenses_range,Range,"",-1) -> -0.05
... A1004: 1000 | B1004: =RANDBETWEEN($P$4*(1+$G$5),$P$4*(1+$G$15)) -> 57632 | C1004: =_xlfn.XLOOKUP(B1004,selling_price_range,Range,"",-1) -> -0.04 | D1004: =RANDBETWEEN($P$5*(1+$G$5),$P$5*(1+$G$15)) -> 5391815 | E1004: =_xlfn.XLOOKUP(D1004,expenses_range,Range,"",-1) -> -0.04

Sheet Sensitivity cases (net income)
A1: Engie company
A2: Sensitivity cases with net income
A3: [AZN Manat]
A4: Cost per Mwh | B4: =cost_per_kwh*1000000 -> 60000
A5: Volume (Mwh) | B5: 20
A6: Turbines | B6: 5
A7: Reveneue | B7: =PRODUCT(B4:B6) -> 6000000
A8: Expenses | B8: =expenses_example -> 5604581.6
A9: EBITDA | B9: =B7-B8 -> 395418.4
A10: Taxes | B10: =B9*income_tax -> 79083.679
A11: Net income | B11: =B9-B10 -> 316334.72
D12: Expenses
D13: {=TRANSPOSE(Range)} -> -0.05 | E13: -0.04 | F13: -0.03 | G13: -0.02 | H13: -0.01 | I13: 0 | J13: 0.01 | K13: 0.02 | L13: 0.03 | M13: 0.04 | N13: 0.05
C14: =B11 -> 316334.72 | D14: {=TRANSPOSE(expenses_range)} -> 5324352.5 | E14: 5380398.3 | F14: 5436444.2 | G14: 5492490 | H14: 5548535.8 | I14: 5604581.6 | J14: 5660627.4 | K14: 5716673.2 | L14: 5772719.1 | M14: 5828764.9 | N14: 5884810.7
A15: Selling price | B15: {=Range} -> -0.05 | C15: {=selling_price_range} -> 57000 | D15: 296032.46 | E15: 466591.16 | F15: 589393.43 | G15: 668805.56 | H15: 707717.5 | I15: 707717.5 | J15: 669194.68 | K15: 591378.57 | L15: 472319.93 | M15: 308812.73 | N15: 96253.363
B16: -0.04 | C16: 57600 | D16: 137040.7 | E16: 306663.07 | F16: 428791.18 | G16: 507767.35 | H16: 546465.68 | I16: 546465.68 | J16: 508154.34 | K16: 430765.42 | L16: 312360.38 | M16: 149750.8 | N16: -61641.66
B17: -0.03 | C17: 58200 | D17: 28992.423 | E17: 197683.61 | F17: 319141.26 | G17: 397683.87 | H17: 436169.75 | I17: 436169.75 | J17: 398068.73 | K17: 321104.67 | L17: 203349.65 | M17: 41632.752 | N17: -168599.21
B18: -0.02 | C18: 58800 | D18: -32781.09 | E18: 134984.02 | F18: 255774.89 | G18: 333886.33 | H18: 372160.93 | I18: 372160.93 | J18: 334269.07 | K18: 257727.52 | L18: 140618.95 | M18: -20210.154 | N18: -229287.99
B19: -0.01 | C19: 59400 | D19: -51369.727 | E19: 115474.39 | F19: 235602.15 | G19: 313284.77 | H19: 351349.25 | I19: 351349.25 | J19: 313665.41 | K19: 237544.06 | L19: 121078.39 | M19: -38867.803 | N19: -246797.85
B20: 0 | C20: 60000 | D20: -28471.3 | E20: 137456.88 | F20: 256925.16 | G20: 334181.32 | H20: 372036.84 | I20: 372036.84 | J20: 334559.88 | K20: 258856.41 | L20: 143030.11 | M20: -16038.008 | N20: -222826.56
B21: 0.01 | C21: 60600 | D21: 35498.75 | E21: 200516.02 | F21: 319328.45 | G21: 396160.49 | H21: 433808.19 | I21: 433808.19 | J21: 396536.97 | K21: 321249.1 | L21: 206058.66 | M21: 47863.786 | N21: -157789.55
B22: 0.02 | C22: 61200 | D22: 141365.06 | E22: 305476.42 | F22: 423636.6 | G22: 500046.85 | H22: 537487.87 | I22: 537487.87 | J22: 500421.26 | K22: 425546.7 | L22: 310988.63 | M22: 153662.22 | N22: -50862.125
B23: 0.03 | C23: 61800 | D23: 291212.9 | E23: 454423.33 | F23: 571934.83 | G23: 647925.61 | H23: 685161.09 | I23: 685161.09 | J23: 648297.96 | K23: 573834.45 | L23: 459905.28 | M23: 303442.55 | N23: 100041
B24: 0.04 | C24: 62400 | D24: 488471.57 | E24: 650786 | F24: 767652.4 | G24: 843226 | H24: 880257.06 | I24: 880257.06 | J24: 843596.31 | K24: 769541.59 | L24: 656237.86 | M24: 500634.08 | N24: 298349.16
B25: 0.05 | C25: 63000 | D25: 738064.94 | E25: 899488.31 | F25: 1015713.1 | G25: 1090871.9 | H25: 1127699.6 | I25: 1127699.6 | J25: 1091240.1 | K25: 1017591.9 | L25: 904910.24 | M25: 750160.68 | N25: 548986.26
A26: Differences in the net income with different selling price and expenses

Sheet Market Share
A1: Engie company
A2: Market share
A4: Share according to market capitalization | F4: Market Share | I4: Countries | J4: Revenue per region | K4: % of total
A5: Energy industry | B5: Revenue | C5: Electricity industry | D5: Revenue2 | F5: Revenue in renewables | G5: Revenue | I5: France | J5: 24341 | K5: 0.4208
A6: Engie $b | B6: 30.24 | C6: Engie $b | D6: 30.24 | F6: Engie renew revenue €b | G6: 3661 | H6: Source | I6: Belgium | J6: 4352 | K6: 0.0752
A7: Industry total $b | B7: 8295 | C7: Industry total $b | D7: 2510 | E7: Source | F7: Renew energy market size €b | G7: 966000 | H7: Source | I7: Other EU | J7: 12501 | K7: 0.2161
A8: Share in energy industry | B8: 0.0036 | C8: Share in electricity industry | D8: 0.012 | F8: Market Share | G8: 0.0038 | I8: Other European countries | J8: 3110 | K8: 0.0538
I9: North America | J9: 4752 | K9: 0.0821
I10: Asia, Middle East & Oceania | J10: 4441 | K10: 0.0768
I11: South America | J11: 4053 | K11: 0.0701
I12: Africa | J12: 297 | K12: 0.0051
I13: Total | J13: 57847
I14: Source
